phpenv.py
phpenv-0.1.1.dist-info/DESCRIPTION.rst
phpenv-0.1.1.dist-info/METADATA
phpenv-0.1.1.dist-info/RECORD
phpenv-0.1.1.dist-info/WHEEL
phpenv-0.1.1.dist-info/entry_points.txt
phpenv-0.1.1.dist-info/metadata.json
phpenv-0.1.1.dist-info/top_level.txt
