Metadata-Version: 2.0
Name: phpenv
Version: 0.1.1
Summary: Php virtual environment builder
Home-page: https://github.com/lomonosow/phpenv
Author: Lomonosow
Author-email: lomonosow93@gmail.com
License: MIT
Platform: any
